py_np4vtt/__init__.py
py_np4vtt/data_format.py
py_np4vtt/data_import.py
py_np4vtt/model_ann.py
py_np4vtt/model_lconstant.py
py_np4vtt/model_loclogit.py
py_np4vtt/model_logistic.py
py_np4vtt/model_rouwendal.py
py_np4vtt/model_rv.py
py_np4vtt/plots.py
py_np4vtt/utils.py
py_np4vtt-1.0.6.dist-info/WHEEL
py_np4vtt-1.0.6.dist-info/METADATA
py_np4vtt-1.0.6.dist-info/RECORD
