Metadata-Version: 2.1
Name: py-np4vtt
Version: 1.0.6
Summary: Python library providing NonParametric models for Value of Travel Time analysis
Home-page: https://gitlab.tudelft.nl/np4vtt/py-np4vtt
Author: José Ignacio Hernández
Author-email: J.I.Hernandez@tudelft.nl
Requires-Python: >=3.8,<=3.10
Classifier: Programming Language :: Python :: 3
Classifier: Programming Language :: Python :: 3.10
Classifier: Programming Language :: Python :: 3.8
Classifier: Programming Language :: Python :: 3.9
Requires-Dist: matplotlib (>=3.5.1,<4.0.0)
Requires-Dist: numdifftools (>=0.9.40,<0.10.0)
Requires-Dist: pandas (>=1.3.1,<2.0.0)
Requires-Dist: scikit-learn (>=1.0.2,<2.0.0)
Requires-Dist: scipy (>=1.7.1,<2.0.0)
Project-URL: Repository, https://gitlab.tudelft.nl/np4vtt/py-np4vtt
